pybbi.libs/libpcre-6b975b27.so.1.2.0
pybbi.libs/libkrb5support-73f3f43d.so.0.1
pybbi.libs/libssl-e50c59ab.so.1.0.2k
pybbi.libs/libkeyutils-19c64d08.so.1.5
pybbi.libs/libk5crypto-47ac5e52.so.3.1
pybbi.libs/libgssapi_krb5-fec99a71.so.2.2
pybbi.libs/libkrb5-90a0ef7c.so.3.3
pybbi.libs/libpng15-7864b8f1.so.15.13.0
pybbi.libs/libcom_err-057ba42b.so.2.1
pybbi.libs/libcrypto-13880bfc.so.1.0.2k
pybbi.libs/libselinux-ae24b712.so.1
bbi/cbbi.cpython-312-aarch64-linux-gnu.so
bbi/cbbi.c
bbi/cbbi.pyx
bbi/__init__.py
bbi/cbbi.pxd
bbi/_bbi.py
pybbi-0.4.1.dist-info/top_level.txt
pybbi-0.4.1.dist-info/RECORD
pybbi-0.4.1.dist-info/LICENSE
pybbi-0.4.1.dist-info/METADATA
pybbi-0.4.1.dist-info/WHEEL
