Metadata-Version: 2.1
Name: pybbi
Version: 0.4.1
Summary: Python bindings to the UCSC source for Big Binary Indexed (bigWig/bigBed) files.
Author-email: Nezar Abdennur <nabdennur@gmail.com>
License: MIT
Project-URL: homepage, https://github.com/nvictus/pybbi
Project-URL: documentation, https://github.com/nvictus/pybbi#README.md
Project-URL: repository, https://github.com/nvictus/pybbi
Keywords: genomics,bioinformatics,bigwig,bigbed,bigbinaryindexed,bbi,ucsc
Classifier: Development Status :: 4 - Beta
Classifier: License :: OSI Approved :: MIT License
Classifier: Operating System :: POSIX
Classifier: Operating System :: Unix
Classifier: Operating System :: MacOS
Classifier: Topic :: Scientific/Engineering :: Bio-Informatics
Classifier: Programming Language :: Python
Classifier: Programming Language :: Python :: 3
Classifier: Programming Language :: Python :: 3.9
Classifier: Programming Language :: Python :: 3.10
Classifier: Programming Language :: Python :: 3.11
Classifier: Programming Language :: Python :: 3.12
Classifier: Programming Language :: Python :: 3.13
Requires-Python: >=3.7
License-File: LICENSE
Requires-Dist: numpy
Provides-Extra: test
Requires-Dist: pytest; extra == "test"
Requires-Dist: pandas; extra == "test"
